chap5/divider.v
`timescale 1ns/1ps

module full_subtractor(
    input wire a,
    input wire b,
    input wire bi,
    output wire d,
    output wire bl
);
    assign #1 d = a ^ b ^ bi;
    assign #1 bl = ((~a) & (b ^ bi)) | (b & bi);

endmodule

module conditional_subtractor #(
    parameter n_bits = 4
)(
    input wire [n_bits - 1 : 0] a,
    input wire [n_bits - 1 : 0] b,
    input wire initial_borrow,
    output reg [n_bits - 1 : 0] result,
    output wire [n_bits - 1 : 0] intermediate_borrows
);

    wire [n_bits - 1 : 0] subtraction_result;

    full_subtractor fs_0 (
        .a(a[0]),
        .b(b[0]),
        .bi(initial_borrow),
        .d(subtraction_result[0]),
        .bl(intermediate_borrows[0])
    );

    genvar i;
    generate
        for (i = 1; i < n_bits; i = i + 1) begin
            full_subtractor fs (
                .a(a[i]),
                .b(b[i]),
                .bi(intermediate_borrows[i - 1]),
                .d(subtraction_result[i]),
                .bl(intermediate_borrows[i])
            );
        end
    endgenerate

    always @(*) begin
        if (intermediate_borrows[n_bits - 1])
            result = a;
        else
            result = subtraction_result;
    end

endmodule

module unsigned_divider #(
    parameter n_bits = 4
)(
    input wire [n_bits - 1 : 0] dividend,
    input wire [n_bits - 1 : 0] divisor,
    output wire [n_bits - 1 : 0] quotient,
    output wire [n_bits - 1 : 0] remainder,
    output wire zero_flag
);

    wire [n_bits - 1 : 0] subtraction_pathway [0 : n_bits - 1];
    wire [n_bits - 1 : 0] borrows [0 : n_bits - 1];

    assign zero_flag = (divisor == {n_bits{1'b0}});
    assign remainder = subtraction_pathway[n_bits - 1];

    conditional_subtractor #(
        .n_bits(n_bits)
    ) csub_init (
        .a({{(n_bits - 1){1'b0}}, dividend[n_bits - 1]}),
        .b(divisor),
        .initial_borrow(1'b0),
        .result(subtraction_pathway[0]),
        .intermediate_borrows(borrows[0])
    );

    genvar i;
    generate
        for (i = 1; i < n_bits; i = i + 1) begin : gen_csubs 
            conditional_subtractor #(
                .n_bits(n_bits)
            ) csub (
                .a({subtraction_pathway[i - 1][n_bits - 2 : 0], dividend[n_bits - 1 - i]}),
                .b(divisor),
                .initial_borrow(1'b0),
                .result(subtraction_pathway[i]),
                .intermediate_borrows(borrows[i])
            );
        end

        for (i = 0; i < n_bits; i = i + 1) begin : gen_quotient
            assign quotient[i] = ~borrows[n_bits - 1 - i][n_bits - 1];
        end
    endgenerate

endmodule

chap5/divider_tb.v
`timescale 1ns/1ps

module divider_tb;
    reg [3:0] a, b;
    wire [3:0] quotient, remainder;
    wire zf;

    unsigned_divider #(
        .n_bits(4)
    ) dut (
        .dividend(a),
        .divisor(b),
        .quotient(quotient),
        .remainder(remainder),
        .zero_flag(zf)
    );

    initial begin
        $dumpfile("dump.vcd");
        $dumpvars(0, divider_tb);

        a = 4'b1011;
        b = 4'b0011;

        #30;

        $display("Quotient: %d, Remainder: %d\n", quotient, remainder);
        $display("ZF: %b\n", zf);
    end
endmodule

chap5/dump.vcd
$date
	Sun Aug 23 22:49:59 2026
$end
$version
	Icarus Verilog
$end
$timescale
	1ps
$end
$scope module divider_tb $end
$var wire 1 ! zf $end
$var wire 4 " remainder [3:0] $end
$var wire 4 # quotient [3:0] $end
$var reg 4 $ a [3:0] $end
$var reg 4 % b [3:0] $end
$scope module dut $end
$var wire 4 & dividend [3:0] $end
$var wire 4 ' divisor [3:0] $end
$var wire 4 ( remainder [3:0] $end
$var wire 1 ! zero_flag $end
$var wire 4 ) quotient [3:0] $end
$var parameter 32 * n_bits $end
$scope begin gen_csubs[1] $end
$var parameter 2 + i $end
$scope module csub $end
$var wire 4 , a [3:0] $end
$var wire 4 - b [3:0] $end
$var wire 1 . initial_borrow $end
$var wire 4 / subtraction_result [3:0] $end
$var wire 4 0 intermediate_borrows [3:0] $end
$var parameter 32 1 n_bits $end
$var reg 4 2 result [3:0] $end
$scope begin genblk1[1] $end
$var parameter 2 3 i $end
$scope module fs $end
$var wire 1 4 a $end
$var wire 1 5 b $end
$var wire 1 6 bi $end
$var wire 1 7 bl $end
$var wire 1 8 d $end
$upscope $end
$upscope $end
$scope begin genblk1[2] $end
$var parameter 3 9 i $end
$scope module fs $end
$var wire 1 : a $end
$var wire 1 ; b $end
$var wire 1 < bi $end
$var wire 1 = bl $end
$var wire 1 > d $end
$upscope $end
$upscope $end
$scope begin genblk1[3] $end
$var parameter 3 ? i $end
$scope module fs $end
$var wire 1 @ a $end
$var wire 1 A b $end
$var wire 1 B bi $end
$var wire 1 C bl $end
$var wire 1 D d $end
$upscope $end
$upscope $end
$scope module fs_0 $end
$var wire 1 E a $end
$var wire 1 F b $end
$var wire 1 . bi $end
$var wire 1 G bl $end
$var wire 1 H d $end
$upscope $end
$upscope $end
$upscope $end
$scope begin gen_csubs[2] $end
$var parameter 3 I i $end
$scope module csub $end
$var wire 4 J a [3:0] $end
$var wire 4 K b [3:0] $end
$var wire 1 L initial_borrow $end
$var wire 4 M subtraction_result [3:0] $end
$var wire 4 N intermediate_borrows [3:0] $end
$var parameter 32 O n_bits $end
$var reg 4 P result [3:0] $end
$scope begin genblk1[1] $end
$var parameter 2 Q i $end
$scope module fs $end
$var wire 1 R a $end
$var wire 1 S b $end
$var wire 1 T bi $end
$var wire 1 U bl $end
$var wire 1 V d $end
$upscope $end
$upscope $end
$scope begin genblk1[2] $end
$var parameter 3 W i $end
$scope module fs $end
$var wire 1 X a $end
$var wire 1 Y b $end
$var wire 1 Z bi $end
$var wire 1 [ bl $end
$var wire 1 \ d $end
$upscope $end
$upscope $end
$scope begin genblk1[3] $end
$var parameter 3 ] i $end
$scope module fs $end
$var wire 1 ^ a $end
$var wire 1 _ b $end
$var wire 1 ` bi $end
$var wire 1 a bl $end
$var wire 1 b d $end
$upscope $end
$upscope $end
$scope module fs_0 $end
$var wire 1 c a $end
$var wire 1 d b $end
$var wire 1 L bi $end
$var wire 1 e bl $end
$var wire 1 f d $end
$upscope $end
$upscope $end
$upscope $end
$scope begin gen_csubs[3] $end
$var parameter 3 g i $end
$scope module csub $end
$var wire 4 h a [3:0] $end
$var wire 4 i b [3:0] $end
$var wire 1 j initial_borrow $end
$var wire 4 k subtraction_result [3:0] $end
$var wire 4 l intermediate_borrows [3:0] $end
$var parameter 32 m n_bits $end
$var reg 4 n result [3:0] $end
$scope begin genblk1[1] $end
$var parameter 2 o i $end
$scope module fs $end
$var wire 1 p a $end
$var wire 1 q b $end
$var wire 1 r bi $end
$var wire 1 s bl $end
$var wire 1 t d $end
$upscope $end
$upscope $end
$scope begin genblk1[2] $end
$var parameter 3 u i $end
$scope module fs $end
$var wire 1 v a $end
$var wire 1 w b $end
$var wire 1 x bi $end
$var wire 1 y bl $end
$var wire 1 z d $end
$upscope $end
$upscope $end
$scope begin genblk1[3] $end
$var parameter 3 { i $end
$scope module fs $end
$var wire 1 | a $end
$var wire 1 } b $end
$var wire 1 ~ bi $end
$var wire 1 !" bl $end
$var wire 1 "" d $end
$upscope $end
$upscope $end
$scope module fs_0 $end
$var wire 1 #" a $end
$var wire 1 $" b $end
$var wire 1 j bi $end
$var wire 1 %" bl $end
$var wire 1 &" d $end
$upscope $end
$upscope $end
$upscope $end
$scope begin gen_quotient[0] $end
$var parameter 2 '" i $end
$upscope $end
$scope begin gen_quotient[1] $end
$var parameter 2 (" i $end
$upscope $end
$scope begin gen_quotient[2] $end
$var parameter 3 )" i $end
$upscope $end
$scope begin gen_quotient[3] $end
$var parameter 3 *" i $end
$upscope $end
$scope module csub_init $end
$var wire 4 +" a [3:0] $end
$var wire 4 ," b [3:0] $end
$var wire 1 -" initial_borrow $end
$var wire 4 ." subtraction_result [3:0] $end
$var wire 4 /" intermediate_borrows [3:0] $end
$var parameter 32 0" n_bits $end
$var reg 4 1" result [3:0] $end
$scope begin genblk1[1] $end
$var parameter 2 2" i $end
$scope module fs $end
$var wire 1 3" a $end
$var wire 1 4" b $end
$var wire 1 5" bi $end
$var wire 1 6" bl $end
$var wire 1 7" d $end
$upscope $end
$upscope $end
$scope begin genblk1[2] $end
$var parameter 3 8" i $end
$scope module fs $end
$var wire 1 9" a $end
$var wire 1 :" b $end
$var wire 1 ;" bi $end
$var wire 1 <" bl $end
$var wire 1 =" d $end
$upscope $end
$upscope $end
$scope begin genblk1[3] $end
$var parameter 3 >" i $end
$scope module fs $end
$var wire 1 ?" a $end
$var wire 1 @" b $end
$var wire 1 A" bi $end
$var wire 1 B" bl $end
$var wire 1 C" d $end
$upscope $end
$upscope $end
$scope module fs_0 $end
$var wire 1 D" a $end
$var wire 1 E" b $end
$var wire 1 -" bi $end
$var wire 1 F" bl $end
$var wire 1 G" d $end
$upscope $end
$upscope $end
$upscope $end
$upscope $end
$enddefinitions $end
$comment Show the parameter values. $end
$dumpall
b11 >"
b10 8"
b1 2"
b100 0"
b11 *"
b10 )"
b1 ("
b0 '"
b11 {
b10 u
b1 o
b100 m
b11 g
b11 ]
b10 W
b1 Q
b100 O
b10 I
b11 ?
b10 9
b1 3
b100 1
b1 +
b100 *
$end
#0
$dumpvars
xG"
xF"
1E"
1D"
xC"
xB"
xA"
0@"
0?"
x="
x<"
x;"
0:"
09"
x7"
x6"
x5"
14"
03"
bx 1"
bx /"
bx ."
0-"
b11 ,"
b1 +"
x&"
x%"
1$"
1#"
x""
x!"
x~
0}
x|
xz
xy
xx
0w
xv
xt
xs
xr
1q
xp
bx n
bx l
bx k
0j
b11 i
bx1 h
xf
xe
1d
1c
xb
xa
x`
0_
x^
x\
x[
xZ
0Y
xX
xV
xU
xT
1S
xR
bx P
bx N
bx M
0L
b11 K
bx1 J
xH
xG
1F
0E
xD
xC
xB
0A
x@
x>
x=
x<
0;
x:
x8
x7
x6
15
x4
bx 2
bx 0
bx /
0.
b11 -
bx0 ,
bx )
bx (
b11 '
b1011 &
b11 %
b1011 $
bx #
bx "
0!
$end
#1000
04
1R
0p
bx00 ,
bx11 J
bx01 h
05"
16
0T
0r
bx0 1"
bx1 2
bx0 P
bx0 "
bx0 (
bx0 n
bx0 /"
0F"
bx1 0
1G
bx0 N
0e
bx0 l
0%"
bx0 ."
0G"
bx1 /
1H
bx0 M
0f
bx0 k
0&"
#2000
0v
0X
1:
bx001 h
bx011 J
bx100 ,
0Z
1x
bx00 P
bx10 "
bx10 (
bx10 n
1;"
1<
bx01 2
bx10 1"
bx00 N
0U
bx10 l
1s
bx01 /
08
bx00 M
0V
bx10 k
1t
bx10 /"
16"
bx11 0
17
bx10 ."
17"
#3000
0^
0|
1@
b11 J
b1 h
b1100 ,
1~
0B
bx110 "
bx110 (
bx110 n
bx001 2
0`
bx000 P
1A"
bx110 1"
bx110 l
1y
bx011 0
0=
bx110 k
1z
bx000 M
0\
bx001 /
0>
bx000 N
0[
bx110 /"
1<"
bx110 ."
1="
#4000
14
0:
0@
b110 #
b110 )
b10 ,
b1 "
b1 (
b1 n
b1001 2
b0 P
b1 1"
b1110 l
1!"
b0 M
0b
b1110 k
1""
b1001 /
1D
b11 0
0C
b0 N
0a
b1110 /"
1B"
b1110 ."
1C"
#5000
1X
1^
b1111 J
1B
b111 2
b111 0
1=
18
1>
b111 /
0D
#6000
b1001 "
b1001 (
b1001 n
1|
0R
0^
b1001 h
b10 #
b10 )
b101 J
b1100 P
b10 2
1\
b1100 M
1b
b1111 0
1C
b1111 /
1D
#7000
1v
b11 #
b11 )
b1101 h
1Z
b110 "
b110 (
b110 n
b110 P
b110 l
0!"
b10 N
1U
b110 k
0""
1V
b110 M
0b
#8000
0|
b101 h
0~
b10 "
b10 (
b10 n
b10 P
b10 l
0y
b10 k
0z
b10 M
0\
