chap3/19.v
`timescale 1ns/1ps

module circuit(
    input wire a,
    input wire b,
    output reg f,
    output reg g
);
    reg xor1, nand1;

    always @(*) begin
        xor1 <= #10 a ^ b;
        nand1 <= #5 ~(a & b);
        f <= #5 ~(a & xor1);
        g <= #10 xor1 ^ nand1;
    end

endmodule

chap3/19_sim.v
`timescale 1ns/1ps

module tb_circuit;
    reg a, b;
    wire f, g;

    circuit uut (
        .a(a),
        .b(b),
        .f(f),
        .g(g)
    );

    initial begin
        $dumpfile("dump.vcd");
        $dumpvars(0, tb_circuit);

        a = 1'b0; b = 1'b0; #3;

        a = 1'b1; #5;

        a = 1'b0; #5;

        b = 1'b1; #5;

        a = 1'b1; #5;

        a = 1'b0; #20;

        $finish;
    end
endmodule

chap3/dump.vcd
$date
	Tue Jul 21 19:46:45 2026
$end
$version
	Icarus Verilog
$end
$timescale
	1ps
$end
$scope module tb_circuit $end
$var wire 1 ! g $end
$var wire 1 " f $end
$var reg 1 # a $end
$var reg 1 $ b $end
$scope module uut $end
$var wire 1 # a $end
$var wire 1 $ b $end
$var reg 1 " f $end
$var reg 1 ! g $end
$var reg 1 % nand1 $end
$var reg 1 & xor1 $end
$upscope $end
$upscope $end
$enddefinitions $end
$comment Show the parameter values. $end
$dumpall
$end
#0
$dumpvars
x&
x%
0$
0#
x"
x!
$end
#3000
1#
#5000
1"
1%
#8000
x"
0#
#10000
0&
#13000
1"
1&
1$
#18000
0&
1#
#20000
1!
#23000
1"
0%
0!
1&
0#
#28000
1%
1!
0&
#33000
1&
#43000
0!
