chap8/string_detector.v
module string_detector(
    input wire clk,
    input wire in,
    input wire reset,
    output reg out
);

    reg [2:0] state;

    always @(*) begin
        case (state)
            3'd6: begin
                if (in) out = 1'b0;
                else out = 1'b1;
            end
            default: out = 1'b0;
        endcase
    end

    always @(posedge clk) begin
        if (reset)
            state <= 3'b000;
        else begin
            case (state)
                3'd0: begin
                    if (in) state <= 3'd2;
                    else state <= 3'd1;
                end
                3'd1: begin
                    if (in) state <= 3'd4;
                    else state <= 3'd3;
                end
                3'd2: begin
                    if (in) state <= 3'd3;
                    else state <= 3'd4;
                end
                3'd3: state <= 3'd5;
                3'd4: begin
                    if (in) state <= 3'd6;
                    else state <= 3'd5;
                end
                default: state <= 3'd0;
            endcase
        end
    end

endmodule

chap8/string_detector_tb.v
`timescale 1ns/1ps

module string_detector_tb;
    reg clk, in, reset;
    wire out;

    parameter CLK_PERIOD = 10;

    string_detector dut (
        .clk(clk),
        .in(in),
        .reset(reset),
        .out(out)
    );

    initial begin
        clk = 1'b0;
        forever #(CLK_PERIOD / 2) clk = ~clk;
    end

    initial begin
        $dumpfile("dump.vcd");
        $dumpvars(0, string_detector_tb);

        reset = 1'b1;

        #6;

        reset = 1'b0;

        in = 1'b1;

        #10;

        in = 1'b0;

        #10;

        in = 1'b1;
        
        #10;

        in = 1'b0;

        #10;

        $finish;
    end

endmodule

chap8/dump.vcd
$date
	Mon Aug 24 15:07:28 2026
$end
$version
	Icarus Verilog
$end
$timescale
	1ps
$end
$scope module string_detector_tb $end
$var wire 1 ! out $end
$var parameter 32 " CLK_PERIOD $end
$var reg 1 # clk $end
$var reg 1 $ in $end
$var reg 1 % reset $end
$scope module dut $end
$var wire 1 # clk $end
$var wire 1 $ in $end
$var wire 1 % reset $end
$var reg 1 ! out $end
$var reg 3 & state [2:0] $end
$upscope $end
$upscope $end
$enddefinitions $end
$comment Show the parameter values. $end
$dumpall
b1010 "
$end
#0
$dumpvars
bx &
1%
x$
0#
x!
$end
#5000
0!
b0 &
1#
#6000
1$
0%
#10000
0#
#15000
b10 &
1#
#16000
0$
#20000
0#
#25000
b100 &
1#
#26000
1$
#30000
0#
#35000
b110 &
1#
#36000
1!
0$
#40000
0#
#45000
0!
b0 &
1#
