chap8/communicating_fsms.v
module fsm_a(
    input wire clk,
    input wire up,
    input wire reset,
    input wire [1:0] state_b,
    output reg [1:0] state
);

    always @(posedge clk) begin
        if (reset)
            state <= 2'b00;
        else begin
            case (state)
                2'b11: begin
                    if (up && state_b == 2'b10)
                        state <= 2'b00;
                    else if (!up && state_b == 2'b00)
                        state <= 2'b10;
                end
                default: begin
                    if (up)
                        state <= state + 1;
                    else
                        state <= state - 1;
                end
            endcase
        end
    end

endmodule

module fsm_b(
    input wire clk,
    input wire up,
    input wire reset,
    input wire [1:0] state_a,
    output reg [1:0] state
);

    always @(posedge clk) begin
        if (reset)
            state <= 2'b11;
        else begin
            case (state)
                2'b11: begin
                    if (up && state_a == 2'b10)
                        state <= 2'b00;
                    else if (!up && state_a == 2'b00)
                        state <= 2'b10;
                end
                default: begin
                    if (up)
                        state <= state + 1;
                    else
                        state <= state - 1;
                end
            endcase
        end
    end

endmodule

module binary_counter(
    input wire clk,
    input wire up,
    input wire reset,
    output reg [2:0] state
);
    wire [1:0] state_a, state_b;

    fsm_a lower_fsm (
        .clk(clk),
        .up(up),
        .reset(reset),
        .state_b(state_b),
        .state(state_a)
    );

    fsm_b upper_fsm (
        .clk(clk),
        .up(up),
        .reset(reset),
        .state_a(state_a),
        .state(state_b)
    );

    always @(*) begin
        if (state_a == 2'b11)
            state = state_b + 2'd3;
        else
            state = state_a;
    end

endmodule

chap8/communicating_fsms_tb.v
`timescale 1ns/1ps

module binary_counter_tb;
    reg clk, up, reset;
    wire [2:0] state;

    binary_counter dut (
        .clk(clk),
        .up(up),
        .reset(reset),
        .state(state)
    );

    parameter CLK_PERIOD = 4;

    initial begin
        clk = 1'b0;
        forever #(CLK_PERIOD / 2) clk = ~clk;
    end

    initial begin
        $dumpfile("dump.vcd");
        $dumpvars(0, binary_counter_tb);

        reset = 1'b1; #3;
        reset = 1'b0; up = 1'b1;

        #100;

        $finish;
    end

endmodule

chap8/dump.vcd
$date
	Mon Aug 24 15:41:52 2026
$end
$version
	Icarus Verilog
$end
$timescale
	1ps
$end
$scope module binary_counter_tb $end
$var wire 3 ! state [2:0] $end
$var parameter 32 " CLK_PERIOD $end
$var reg 1 # clk $end
$var reg 1 $ reset $end
$var reg 1 % up $end
$scope module dut $end
$var wire 1 # clk $end
$var wire 1 $ reset $end
$var wire 1 % up $end
$var wire 2 & state_b [1:0] $end
$var wire 2 ' state_a [1:0] $end
$var reg 3 ( state [2:0] $end
$scope module lower_fsm $end
$var wire 1 # clk $end
$var wire 1 $ reset $end
$var wire 1 % up $end
$var wire 2 ) state_b [1:0] $end
$var reg 2 * state [1:0] $end
$upscope $end
$scope module upper_fsm $end
$var wire 1 # clk $end
$var wire 1 $ reset $end
$var wire 2 + state_a [1:0] $end
$var wire 1 % up $end
$var reg 2 , state [1:0] $end
$upscope $end
$upscope $end
$upscope $end
$enddefinitions $end
$comment Show the parameter values. $end
$dumpall
b100 "
$end
#0
$dumpvars
bx ,
bx +
bx *
bx )
bx (
bx '
bx &
x%
1$
0#
bx !
$end
#2000
b0 !
b0 (
b0 '
b0 *
b0 +
b11 &
b11 )
b11 ,
1#
#3000
1%
0$
#4000
0#
#6000
b1 !
b1 (
b1 '
b1 *
b1 +
1#
#8000
0#
#10000
b10 !
b10 (
b10 '
b10 *
b10 +
1#
#12000
0#
#14000
b11 !
b11 (
b0 &
b0 )
b0 ,
b11 '
b11 *
b11 +
1#
#16000
0#
#18000
b100 !
b100 (
b1 &
b1 )
b1 ,
1#
#20000
0#
#22000
b101 !
b101 (
b10 &
b10 )
b10 ,
1#
#24000
0#
#26000
b0 !
b0 (
b0 '
b0 *
b0 +
b11 &
b11 )
b11 ,
1#
#28000
0#
#30000
b1 !
b1 (
b1 '
b1 *
b1 +
1#
#32000
0#
#34000
b10 !
b10 (
b10 '
b10 *
b10 +
1#
#36000
0#
#38000
b11 !
b11 (
b0 &
b0 )
b0 ,
b11 '
b11 *
b11 +
1#
#40000
0#
#42000
b100 !
b100 (
b1 &
b1 )
b1 ,
1#
#44000
0#
#46000
b101 !
b101 (
b10 &
b10 )
b10 ,
1#
#48000
0#
#50000
b0 !
b0 (
b0 '
b0 *
b0 +
b11 &
b11 )
b11 ,
1#
#52000
0#
#54000
b1 !
b1 (
b1 '
b1 *
b1 +
1#
#56000
0#
#58000
b10 !
b10 (
b10 '
b10 *
b10 +
1#
#60000
0#
#62000
b11 !
b11 (
b0 &
b0 )
b0 ,
b11 '
b11 *
b11 +
1#
#64000
0#
#66000
b100 !
b100 (
b1 &
b1 )
b1 ,
1#
#68000
0#
#70000
b101 !
b101 (
b10 &
b10 )
b10 ,
1#
#72000
0#
#74000
b0 !
b0 (
b0 '
b0 *
b0 +
b11 &
b11 )
b11 ,
1#
#76000
0#
#78000
b1 !
b1 (
b1 '
b1 *
b1 +
1#
#80000
0#
#82000
b10 !
b10 (
b10 '
b10 *
b10 +
1#
#84000
0#
#86000
b11 !
b11 (
b0 &
b0 )
b0 ,
b11 '
b11 *
b11 +
1#
#88000
0#
#90000
b100 !
b100 (
b1 &
b1 )
b1 ,
1#
#92000
0#
#94000
b101 !
b101 (
b10 &
b10 )
b10 ,
1#
#96000
0#
#98000
b0 !
b0 (
b0 '
b0 *
b0 +
b11 &
b11 )
b11 ,
1#
#100000
0#
#102000
b1 !
b1 (
b1 '
b1 *
b1 +
1#
