chap6/stack2.v
module stack #(
    parameter n_regs = 8,
    parameter word_size = 8,
    parameter bits_of_counter = 3
)(
    input wire clk,
    input wire pop,
    input wire push,
    input wire reset,
    input wire [word_size - 1 : 0] data_input,
    output reg [word_size - 1 : 0] stack_top,
    output reg lifo_empty,
    output reg lifo_full
);
    reg [bits_of_counter - 1 : 0] stack_pointer;
    reg [word_size - 1 : 0] storage [0 : n_regs - 1];
    
    integer i;

    always @(*) begin
        lifo_empty = (stack_pointer == {bits_of_counter{1'b0}});
        lifo_full = (stack_pointer == n_regs);
        if (!lifo_empty)
            stack_top = storage[stack_pointer - 1];
        else
            stack_top = {word_size{1'b0}};
    end

    always @(posedge clk) begin
        if (reset) begin
            for (i = 0; i < n_regs; i = i + 1) begin
                storage[i] <= {word_size{1'b0}};
            end
            stack_pointer <= {bits_of_counter{1'b0}};
        end
        else begin
            case ({pop & ~lifo_empty, push & ~lifo_full})
                2'b01: begin
                    storage[stack_pointer] <= data_input;
                    stack_pointer <= stack_pointer + 1;
                end

                2'b10: begin
                    stack_pointer <= stack_pointer - 1;
                end
            endcase
        end
    end

endmodule

chap6/stack_test2.v
`timescale 1ns/1ps

module stack_tb;

    parameter n_regs = 8;
    parameter word_size = 8;
    parameter bits_of_counter = 4;

    reg clk;
    reg pop;
    reg push;
    reg reset;
    reg [word_size-1:0] data_input;

    wire [word_size-1:0] stack_top;
    wire lifo_empty;
    wire lifo_full;

    integer i;

    stack #(
        .n_regs(n_regs),
        .word_size(word_size),
        .bits_of_counter(bits_of_counter)
    ) dut (
        .clk(clk),
        .pop(pop),
        .push(push),
        .reset(reset),
        .data_input(data_input),
        .stack_top(stack_top),
        .lifo_empty(lifo_empty),
        .lifo_full(lifo_full)
    );

    // 10 ns clock period
    always #5 clk = ~clk;


    // --------------------------------------------------
    // Push task
    // --------------------------------------------------
    task push_value;
        input [word_size-1:0] value;
        begin
            @(negedge clk);
            data_input = value;
            push = 1'b1;
            pop  = 1'b0;

            @(negedge clk);
            push = 1'b0;
        end
    endtask


    // --------------------------------------------------
    // Pop task
    // --------------------------------------------------
    task pop_value;
        begin
            @(negedge clk);
            push = 1'b0;
            pop  = 1'b1;

            @(negedge clk);
            pop = 1'b0;
        end
    endtask


    // --------------------------------------------------
    // Print current stack state
    // --------------------------------------------------
    task print_state;
        begin
            $display(
                "time=%0t  pointer=%0d  empty=%b  full=%b  top=%h",
                $time,
                dut.stack_pointer,
                lifo_empty,
                lifo_full,
                stack_top
            );
        end
    endtask


    initial begin

        // Initial signal values
        clk        = 1'b0;
        reset      = 1'b0;
        pop        = 1'b0;
        push       = 1'b0;
        data_input = {word_size{1'b0}};

        // Waveform output
        $dumpfile("stack_tb.vcd");
        $dumpvars(0, stack_tb);


        // ==================================================
        // TEST 1: Reset
        // ==================================================

        $display("\n--- TEST 1: RESET ---");

        @(negedge clk);
        reset = 1'b1;

        // Reset is synchronous, so it must cross a rising edge.
        @(negedge clk);
        reset = 1'b0;

        #1;
        print_state();

        if (lifo_empty !== 1'b1)
            $display("ERROR: Stack should be empty after reset");

        if (lifo_full !== 1'b0)
            $display("ERROR: Stack should not be full after reset");

        if (stack_top !== {word_size{1'b0}})
            $display(
                "ERROR: Stack top should be zero after reset, got %h",
                stack_top
            );


        // ==================================================
        // TEST 2: Push one value
        // ==================================================

        $display("\n--- TEST 2: PUSH 11 ---");

        push_value(8'h11);
        #1;
        print_state();

        if (stack_top !== 8'h11)
            $display(
                "ERROR: Expected top=11, got %h",
                stack_top
            );

        if (lifo_empty !== 1'b0)
            $display("ERROR: Stack should not be empty");


        // ==================================================
        // TEST 3: Push additional values
        // ==================================================

        $display("\n--- TEST 3: PUSH 22, 33 ---");

        push_value(8'h22);
        print_state();

        if (stack_top !== 8'h22)
            $display(
                "ERROR: Expected top=22, got %h",
                stack_top
            );

        push_value(8'h33);
        print_state();

        if (stack_top !== 8'h33)
            $display(
                "ERROR: Expected top=33, got %h",
                stack_top
            );


        // ==================================================
        // TEST 4: Verify LIFO behavior
        // ==================================================

        $display("\n--- TEST 4: POP 33 ---");

        pop_value();
        #1;
        print_state();

        if (stack_top !== 8'h22)
            $display(
                "ERROR: Expected top=22 after pop, got %h",
                stack_top
            );


        $display("\n--- POP 22 ---");

        pop_value();
        #1;
        print_state();

        if (stack_top !== 8'h11)
            $display(
                "ERROR: Expected top=11 after pop, got %h",
                stack_top
            );


        $display("\n--- POP 11 ---");

        pop_value();
        #1;
        print_state();

        if (lifo_empty !== 1'b1)
            $display(
                "ERROR: Stack should be empty after final pop"
            );


        // ==================================================
        // TEST 5: Pop while empty
        // ==================================================

        $display("\n--- TEST 5: POP WHILE EMPTY ---");

        pop_value();
        #1;
        print_state();

        if (lifo_empty !== 1'b1)
            $display(
                "ERROR: Stack changed after pop while empty"
            );

        if (dut.stack_pointer !== 0)
            $display(
                "ERROR: Pointer changed after pop while empty"
            );


        // ==================================================
        // TEST 6: Fill the stack
        // ==================================================

        $display("\n--- TEST 6: FILL STACK ---");

        for (i = 0; i < n_regs; i = i + 1) begin
            push_value(i + 1);
            print_state();
        end

        if (lifo_full !== 1'b1)
            $display(
                "ERROR: Stack should be full"
            );

        if (dut.stack_pointer !== n_regs)
            $display(
                "ERROR: Expected pointer=%0d, got %0d",
                n_regs,
                dut.stack_pointer
            );

        if (stack_top !== n_regs)
            $display(
                "ERROR: Expected top=%0d, got %h",
                n_regs,
                stack_top
            );


        // ==================================================
        // TEST 7: Push while full
        // ==================================================

        $display("\n--- TEST 7: PUSH WHILE FULL ---");

        push_value(8'hFF);
        #1;
        print_state();

        if (lifo_full !== 1'b1)
            $display(
                "ERROR: Stack should remain full"
            );

        if (dut.stack_pointer !== n_regs)
            $display(
                "ERROR: Pointer changed after push while full"
            );

        if (stack_top !== n_regs)
            $display(
                "ERROR: Top changed after push while full"
            );


        // ==================================================
        // TEST 8: Pop everything
        // ==================================================

        $display("\n--- TEST 8: EMPTY STACK ---");

        for (i = n_regs; i > 0; i = i - 1) begin

            if (stack_top !== i)
                $display(
                    "ERROR: Expected top=%0d, got %h",
                    i,
                    stack_top
                );

            pop_value();
            #1;
            print_state();

        end

        if (lifo_empty !== 1'b1)
            $display(
                "ERROR: Stack should be empty"
            );

        if (dut.stack_pointer !== 0)
            $display(
                "ERROR: Pointer should be zero"
            );


        // ==================================================
        // TEST 9: Reset a non-empty stack
        // ==================================================

        $display("\n--- TEST 9: RESET NON-EMPTY STACK ---");

        push_value(8'hAA);
        push_value(8'hBB);
        push_value(8'hCC);

        print_state();

        @(negedge clk);
        reset = 1'b1;

        @(negedge clk);
        reset = 1'b0;

        #1;
        print_state();

        if (lifo_empty !== 1'b1)
            $display(
                "ERROR: Stack should be empty after reset"
            );

        if (dut.stack_pointer !== 0)
            $display(
                "ERROR: Pointer should be zero after reset"
            );


        // ==================================================
        // Done
        // ==================================================

        $display("\n================================");
        $display("       TESTBENCH COMPLETE");
        $display("================================\n");

        #10;
        $finish;

    end

endmodule

chap6/stack_tb.vcd
$date
	Mon Aug 17 22:58:49 2026
$end
$version
	Icarus Verilog
$end
$timescale
	1ps
$end
$scope module stack_tb $end
$var wire 8 ! stack_top [7:0] $end
$var wire 1 " lifo_full $end
$var wire 1 # lifo_empty $end
$var parameter 32 $ bits_of_counter $end
$var parameter 32 % n_regs $end
$var parameter 32 & word_size $end
$var reg 1 ' clk $end
$var reg 8 ( data_input [7:0] $end
$var reg 1 ) pop $end
$var reg 1 * push $end
$var reg 1 + reset $end
$var integer 32 , i [31:0] $end
$scope module dut $end
$var wire 1 ' clk $end
$var wire 8 - data_input [7:0] $end
$var wire 1 ) pop $end
$var wire 1 * push $end
$var wire 1 + reset $end
$var parameter 32 . bits_of_counter $end
$var parameter 32 / n_regs $end
$var parameter 32 0 word_size $end
$var reg 1 # lifo_empty $end
$var reg 1 " lifo_full $end
$var reg 4 1 stack_pointer [3:0] $end
$var reg 8 2 stack_top [7:0] $end
$var integer 32 3 i [31:0] $end
$upscope $end
$scope task pop_value $end
$upscope $end
$scope task print_state $end
$upscope $end
$scope task push_value $end
$var reg 8 4 value [7:0] $end
$upscope $end
$upscope $end
$enddefinitions $end
$comment Show the parameter values. $end
$dumpall
b1000 0
b1000 /
b100 .
b1000 &
b1000 %
b100 $
$end
#0
$dumpvars
bx 4
bx 3
bx 2
bx 1
b0 -
bx ,
0+
0*
0)
b0 (
0'
x#
x"
bx !
$end
#5000
1'
#10000
1+
0'
#15000
b0 !
b0 2
0"
1#
b0 1
b1000 3
1'
#20000
0+
0'
#21000
b10001 4
#25000
1'
#30000
1*
b10001 (
b10001 -
0'
#35000
b10001 !
b10001 2
0#
b1 1
1'
#40000
0*
0'
#41000
b100010 4
#45000
1'
#50000
1*
b100010 (
b100010 -
0'
#55000
b100010 !
b100010 2
b10 1
1'
#60000
b110011 4
0*
0'
#65000
1'
#70000
1*
b110011 (
b110011 -
0'
#75000
b110011 !
b110011 2
b11 1
1'
#80000
0*
0'
#85000
1'
#90000
1)
0'
#95000
b100010 !
b100010 2
b10 1
1'
#100000
0)
0'
#105000
1'
#110000
1)
0'
#115000
b10001 !
b10001 2
b1 1
1'
#120000
0)
0'
#125000
1'
#130000
1)
0'
#135000
b0 !
b0 2
1#
b0 1
1'
#140000
0)
0'
#145000
1'
#150000
1)
0'
#155000
1'
#160000
0)
0'
#161000
b1 4
b0 ,
#165000
1'
#170000
1*
b1 (
b1 -
0'
#175000
b1 !
b1 2
0#
b1 1
1'
#180000
b10 4
b1 ,
0*
0'
#185000
1'
#190000
1*
b10 (
b10 -
0'
#195000
b10 !
b10 2
b10 1
1'
#200000
b11 4
b10 ,
0*
0'
#205000
1'
#210000
1*
b11 (
b11 -
0'
#215000
b11 !
b11 2
b11 1
1'
#220000
b100 4
b11 ,
0*
0'
#225000
1'
#230000
1*
b100 (
b100 -
0'
#235000
b100 !
b100 2
b100 1
1'
#240000
b101 4
b100 ,
0*
0'
#245000
1'
#250000
1*
b101 (
b101 -
0'
#255000
b101 !
b101 2
b101 1
1'
#260000
b110 4
b101 ,
0*
0'
#265000
1'
#270000
1*
b110 (
b110 -
0'
#275000
b110 !
b110 2
b110 1
1'
#280000
b111 4
b110 ,
0*
0'
#285000
1'
#290000
1*
b111 (
b111 -
0'
#295000
b111 !
b111 2
b111 1
1'
#300000
b1000 4
b111 ,
0*
0'
#305000
1'
#310000
1*
b1000 (
b1000 -
0'
#315000
b1000 !
b1000 2
1"
b1000 1
1'
#320000
b11111111 4
b1000 ,
0*
0'
#325000
1'
#330000
1*
b11111111 (
b11111111 -
0'
#335000
1'
#340000
0*
0'
#345000
1'
#350000
1)
0'
#355000
b111 !
b111 2
0"
b111 1
1'
#360000
0)
0'
#361000
b111 ,
#365000
1'
#370000
1)
0'
#375000
b110 !
b110 2
b110 1
1'
#380000
0)
0'
#381000
b110 ,
#385000
1'
#390000
1)
0'
#395000
b101 !
b101 2
b101 1
1'
#400000
0)
0'
#401000
b101 ,
#405000
1'
#410000
1)
0'
#415000
b100 !
b100 2
b100 1
1'
#420000
0)
0'
#421000
b100 ,
#425000
1'
#430000
1)
0'
#435000
b11 !
b11 2
b11 1
1'
#440000
0)
0'
#441000
b11 ,
#445000
1'
#450000
1)
0'
#455000
b10 !
b10 2
b10 1
1'
#460000
0)
0'
#461000
b10 ,
#465000
1'
#470000
1)
0'
#475000
b1 !
b1 2
b1 1
1'
#480000
0)
0'
#481000
b1 ,
#485000
1'
#490000
1)
0'
#495000
b0 !
b0 2
1#
b0 1
1'
#500000
0)
0'
#501000
b10101010 4
b0 ,
#505000
1'
#510000
1*
b10101010 (
b10101010 -
0'
#515000
b10101010 !
b10101010 2
0#
b1 1
1'
#520000
b10111011 4
0*
0'
#525000
1'
#530000
1*
b10111011 (
b10111011 -
0'
#535000
b10111011 !
b10111011 2
b10 1
1'
#540000
b11001100 4
0*
0'
#545000
1'
#550000
1*
b11001100 (
b11001100 -
0'
#555000
b11001100 !
b11001100 2
b11 1
1'
#560000
0*
0'
#565000
1'
#570000
1+
0'
#575000
b0 !
b0 2
1#
b0 1
b1000 3
1'
#580000
0+
0'
